{
    "recipes": [
      {
        "id": 1,
        "name": "Spaghetti Bolognese",
        "image": "https://img.freepik.com/free-photo/spaghetti-with-bolognese-sauce-wooden-table_123827-22963.jpg",
        "category": "Dinner",
        "ingredients": [
          "200g spaghetti",
          "1 onion",
          "2 garlic cloves",
          "400g ground beef",
          "400g tomato sauce"
        ],
        "instructions": "Cook pasta. Sauté onions, garlic, and ground beef. Add tomato sauce and simmer."
      },
      {
        "id": 2,
        "name": "Chicken Caesar Salad",
        "image": "https://www.shutterstock.com/image-photo/classic-caesar-salad-grilled-chicken-600nw-1738605458.jpg",
        "category": "Lunch",
        "ingredients": [
          "1 chicken breast",
          "1 head romaine lettuce",
          "1/4 cup Caesar dressing",
          "1/4 cup croutons",
          "2 tbsp Parmesan cheese"
        ],
        "instructions": "Grill chicken. Mix lettuce, croutons, Caesar dressing, and Parmesan. Top with chicken."
      },
      {
        "id": 3,
        "name": "Pancakes",
        "image": "https://encrypted-tbn0.gstatic.com/images?q=tbn:ANd9GcQ4TJsceHwjtAUNKrp5suYGG4_-eE88Nqxu4g&s",
        "category": "Breakfast",
        "ingredients": [
          "1 cup flour",
          "1 cup milk",
          "1 egg",
          "2 tbsp sugar",
          "1 tbsp butter"
        ],
        "instructions": "Mix flour, milk, eggs, and sugar. Pour batter onto hot griddle. Flip when bubbly."
      },
      {
        "id": 4,
        "name": "Vegetable Stir-fry",
        "image": "https://t3.ftcdn.net/jpg/01/04/13/56/360_F_104135636_bH0l3ScKrNedCikbIsEgR49I6phhpzuH.jpg",
        "category": "Dinner",
        "ingredients": [
          "2 cups mixed vegetables",
          "2 tbsp soy sauce",
          "1 garlic clove",
          "1 tsp ginger",
          "1 tbsp olive oil"
        ],
        "instructions": "Stir-fry mixed vegetables with soy sauce, garlic, and ginger. Serve with rice."
      },
      {
        "id": 5,
        "name": "Chocolate Cake",
        "image": "https://media.istockphoto.com/id/1370520449/photo/slice-of-chocolate-cake-with-glaze.jpg?s=612x612&w=0&k=20&c=KK-h7w4l0FNA0YMWvkr1X8UrAAB77z0f5tTByBYgReM=",
        "category": "Dessert",
        "ingredients": [
          "1 cup flour",
          "1/2 cup cocoa powder",
          "1 cup sugar",
          "2 eggs",
          "1/2 cup milk"
        ],
        "instructions": "Mix flour, cocoa powder, sugar, eggs, and milk. Bake at 350°F for 30 minutes."
      },
      {
        "id": 6,
        "name": "Grilled Cheese Sandwich",
        "image": "https://encrypted-tbn0.gstatic.com/images?q=tbn:ANd9GcT7sFcgSRCqibSVedVBFAPqQ4fGs-8McyLotQ&s",
        "category": "Lunch",
        "ingredients": [
          "2 slices of bread",
          "2 slices of cheese",
          "1 tbsp butter"
        ],
        "instructions": "Butter bread, add cheese, and grill on medium heat until golden brown."
      },
      {
        "id": 7,
        "name": "Tacos",
        "image": "https://encrypted-tbn0.gstatic.com/images?q=tbn:ANd9GcRDU0EY9DBSKdk8ifngtyt8W43LVWyuQpD4_w&s",
        "category": "Dinner",
        "ingredients": [
          "200g ground beef",
          "1 packet taco seasoning",
          "4 tortillas",
          "1/2 cup shredded lettuce",
          "1/2 cup shredded cheese",
          "1/4 cup salsa"
        ],
        "instructions": "Cook ground beef with taco seasoning. Serve in tortillas with lettuce, cheese, and salsa."
      },
      {
        "id": 8,
        "name": "Avocado Toast",
        "image": "https://images.unsplash.com/photo-1504382262782-5b4ece78642b?w=600&auto=format&fit=crop&q=60&ixlib=rb-4.0.3&ixid=M3wxMjA3fDB8MHxzZWFyY2h8MTF8fGF2b2NhZG8lMjB0b2FzdHxlbnwwfHwwfHx8MA%3D%3D",
        "category": "Breakfast",
        "ingredients": [
          "1 avocado",
          "2 slices of bread",
          "1 tbsp olive oil",
          "Salt",
          "Pepper"
        ],
        "instructions": "Toast bread, mash avocado, and spread on toast. Add salt, pepper, and a drizzle of olive oil."
      },
      {
        "id": 9,
        "name": "Blueberry Muffins",
        "image": "https://www.shutterstock.com/image-photo/closeup-two-delicious-blueberry-muffin-600nw-2483090979.jpg",
        "category": "Dessert",
        "ingredients": [
          "1 1/2 cups flour",
          "1/2 cup sugar",
          "2 eggs",
          "1/2 cup milk",
          "1 cup blueberries"
        ],
        "instructions": "Mix flour, sugar, eggs, milk, and blueberries. Bake at 375°F for 20-25 minutes."
      },
      {
        "id": 10,
        "name": "Omelette",
        "image": "https://cdn.pixabay.com/photo/2015/05/20/16/11/kitchen-775746_1280.jpg",
        "category": "Breakfast",
        "ingredients": [
          "3 eggs",
          "1/4 cup cheese",
          "1/4 cup diced vegetables",
          "1 tbsp butter"
        ],
        "instructions": "Whisk eggs, pour into a hot pan, and cook until set. Add cheese and vegetables."
      },
      {
        "id": 11,
        "name": "Beef Stew",
        "image": "https://www.shutterstock.com/image-photo/irish-stew-st-patricks-day-600nw-2492128995.jpg",
        "category": "Dinner",
        "ingredients": [
          "500g beef",
          "2 carrots",
          "2 potatoes",
          "1 onion",
          "2 cups beef broth"
        ],
        "instructions": "Brown beef, then simmer with carrots, potatoes, and beef broth for 2 hours."
      },
      {
        "id": 12,
        "name": "French Toast",
        "image": "https://t4.ftcdn.net/jpg/01/95/34/53/360_F_195345317_3Fmu3XXrVjzt4I6oSG9qdA2wYW74NyQG.jpg",
        "category": "Breakfast",
        "ingredients": [
          "2 slices of bread",
          "1 egg",
          "1/4 cup milk",
          "1 tbsp butter",
          "1 tsp cinnamon"
        ],
        "instructions": "Mix egg, milk, and cinnamon. Dip bread into the mixture. Cook on hot pan with butter until golden."
      },
      {
        "id": 13,
        "name": "Caesar Wrap",
        "image": "https://media.istockphoto.com/id/589124512/photo/chicken-caesar-salad-sandwich-wraps.jpg?s=612x612&w=0&k=20&c=T3aHb8mKEaFz72HPti5Ep2WPxpZgqFpF962gntN99MY=",
        "category": "Lunch",
        "ingredients": [
          "1 tortilla",
          "1 chicken breast",
          "1/4 cup Caesar dressing",
          "1/4 cup lettuce",
          "2 tbsp Parmesan cheese"
        ],
        "instructions": "Grill chicken. Wrap it with lettuce, Caesar dressing, and Parmesan in a tortilla."
      },
      {
        "id": 14,
        "name": "Tomato Soup",
        "image": "https://img.freepik.com/free-photo/warm-tomato-soup-serve-bowl_1150-42626.jpg",
        "category": "Dinner",
        "ingredients": [
          "4 ripe tomatoes",
          "1 onion",
          "2 garlic cloves",
          "2 cups vegetable broth",
          "1 tbsp olive oil"
        ],
        "instructions": "Sauté onions and garlic. Add chopped tomatoes and vegetable broth. Simmer for 20 minutes and blend."
      },
      {
        "id": 15,
        "name": "Banana Smoothie",
        "image": "https://media.istockphoto.com/id/1170162958/photo/banana-smoothie.jpg?s=612x612&w=0&k=20&c=1vLluqONLlFrtv--RTp-ZYRHVOgAXdneXPS85QwWUNM=",
        "category": "Breakfast",
        "ingredients": [
          "2 bananas",
          "1 cup milk",
          "1/2 cup yogurt",
          "1 tbsp honey"
        ],
        "instructions": "Blend bananas, milk, yogurt, and honey until smooth. Serve chilled."
      }
    ]
  }
  
